aws_wand/__init__.py
aws_wand/iam_admin.py
aws_wand/s3.py
aws_wand/s3_bucket.py
aws_wand/iam/__init__.py
aws_wand/iam/iam_admin.py
aws_wand/iam/iam_handling_api.py
aws_wand/iam/api/__init__.py
aws_wand/iam/api/api.py
aws_wand-1.0.4.dist-info/LICENSE
aws_wand-1.0.4.dist-info/METADATA
aws_wand-1.0.4.dist-info/WHEEL
aws_wand-1.0.4.dist-info/top_level.txt
aws_wand-1.0.4.dist-info/RECORD
