Metadata-Version: 2.1
Name: aws_wand
Version: 1.0.4
Summary: Simple API to train ML models on AWS
Home-page: 
Author: Rodion S.
Author-email: rodion.shyshkin@gmail.com
Classifier: Programming Language :: Python :: 3
Classifier: License :: OSI Approved :: MIT License
Classifier: Operating System :: OS Independent
License-File: LICENSE
